drf_to_mkdoc/__init__.py
drf_to_mkdoc/apps.py
drf_to_mkdoc/conf/__init__.py
drf_to_mkdoc/conf/defaults.py
drf_to_mkdoc/conf/settings.py
drf_to_mkdoc/management/__init__.py
drf_to_mkdoc/management/commands/__init__.py
drf_to_mkdoc/management/commands/build_docs.py
drf_to_mkdoc/management/commands/generate_doc_json.py
drf_to_mkdoc/management/commands/generate_docs.py
drf_to_mkdoc/management/commands/generate_model_docs.py
drf_to_mkdoc/management/commands/update_doc_schema.py
drf_to_mkdoc/static/drf-to-mkdoc/javascripts/endpoints-filter.js
drf_to_mkdoc/static/drf-to-mkdoc/stylesheets/extra.css
drf_to_mkdoc/static/drf-to-mkdoc/stylesheets/endpoints/accessibility.css
drf_to_mkdoc/static/drf-to-mkdoc/stylesheets/endpoints/animations.css
drf_to_mkdoc/static/drf-to-mkdoc/stylesheets/endpoints/badges.css
drf_to_mkdoc/static/drf-to-mkdoc/stylesheets/endpoints/base.css
drf_to_mkdoc/static/drf-to-mkdoc/stylesheets/endpoints/endpoint-content.css
drf_to_mkdoc/static/drf-to-mkdoc/stylesheets/endpoints/endpoints-grid.css
drf_to_mkdoc/static/drf-to-mkdoc/stylesheets/endpoints/filter-section.css
drf_to_mkdoc/static/drf-to-mkdoc/stylesheets/endpoints/fixes.css
drf_to_mkdoc/static/drf-to-mkdoc/stylesheets/endpoints/layout.css
drf_to_mkdoc/static/drf-to-mkdoc/stylesheets/endpoints/loading.css
drf_to_mkdoc/static/drf-to-mkdoc/stylesheets/endpoints/responsive.css
drf_to_mkdoc/static/drf-to-mkdoc/stylesheets/endpoints/sections.css
drf_to_mkdoc/static/drf-to-mkdoc/stylesheets/endpoints/stats.css
drf_to_mkdoc/static/drf-to-mkdoc/stylesheets/endpoints/tags.css
drf_to_mkdoc/static/drf-to-mkdoc/stylesheets/endpoints/theme-toggle.css
drf_to_mkdoc/static/drf-to-mkdoc/stylesheets/endpoints/variables.css
drf_to_mkdoc/utils/__init__.py
drf_to_mkdoc/utils/common.py
drf_to_mkdoc/utils/endpoint_generator.py
drf_to_mkdoc/utils/model_generator.py
drf_to_mkdoc/utils/extractors/__init__.py
drf_to_mkdoc/utils/extractors/query_parameter_extractors.py
drf_to_mkdoc/utils/md_generators/__init__.py
drf_to_mkdoc-1.0.7.dist-info/licenses/LICENSE
drf_to_mkdoc-1.0.7.dist-info/METADATA
drf_to_mkdoc-1.0.7.dist-info/WHEEL
drf_to_mkdoc-1.0.7.dist-info/top_level.txt
drf_to_mkdoc-1.0.7.dist-info/RECORD
