Metadata-Version: 2.4
Name: drf-to-mkdoc
Version: 1.0.7
Summary: Generate Markdown API docs from Django/DRF OpenAPI schema for MkDocs
Author-email: Hossein Shayesteh <shayestehhs1@gmail.com>
Maintainer-email: Hossein Shayesteh <shayestehhs1@gmail.com>
License: MIT
Project-URL: Homepage, https://github.com/shayestehhs/drf-to-mkdoc
Project-URL: Repository, https://github.com/shayestehhs/drf-to-mkdoc
Project-URL: Documentation, https://github.com/shayestehhs/drf-to-mkdoc#readme
Project-URL: Bug Tracker, https://github.com/shayestehhs/drf-to-mkdoc/issues
Keywords: django,django-rest-framework,documentation,mkdocs,api
Classifier: Development Status :: 4 - Beta
Classifier: Intended Audience :: Developers
Classifier: License :: OSI Approved :: MIT License
Classifier: Operating System :: OS Independent
Classifier: Programming Language :: Python :: 3
Classifier: Programming Language :: Python :: 3.8
Classifier: Programming Language :: Python :: 3.9
Classifier: Programming Language :: Python :: 3.10
Classifier: Programming Language :: Python :: 3.11
Classifier: Programming Language :: Python :: 3.12
Classifier: Framework :: Django
Classifier: Framework :: Django :: 3.2
Classifier: Framework :: Django :: 4.0
Classifier: Framework :: Django :: 4.1
Classifier: Framework :: Django :: 4.2
Classifier: Framework :: Django :: 5.0
Classifier: Topic :: Documentation
Classifier: Topic :: Software Development :: Documentation
Requires-Python: >=3.8
License-File: LICENSE
Requires-Dist: Django<6.0,>=3.2
Requires-Dist: djangorestframework<4.0,>=3.12
Requires-Dist: PyYAML>=6.0
Requires-Dist: drf-spectacular>=0.26.0
Requires-Dist: mkdocs>=1.4.0
Requires-Dist: mkdocs-material>=9.0.0
Requires-Dist: coreapi>=2.3.0
Provides-Extra: dev
Requires-Dist: pytest>=7.0.0; extra == "dev"
Requires-Dist: pytest-django>=4.5.0; extra == "dev"
Requires-Dist: black>=22.0.0; extra == "dev"
Requires-Dist: isort>=5.10.0; extra == "dev"
Requires-Dist: flake8>=5.0.0; extra == "dev"
Requires-Dist: mypy>=1.0.0; extra == "dev"
Dynamic: license-file
